closer/__init__.py
closer/closer3.py
closer/exceptions.py
closer/find_remote_control_port.py
closer/remote.py
closer-4.0.5.dist-info/DESCRIPTION.rst
closer-4.0.5.dist-info/METADATA
closer-4.0.5.dist-info/RECORD
closer-4.0.5.dist-info/WHEEL
closer-4.0.5.dist-info/entry_points.txt
closer-4.0.5.dist-info/metadata.json
closer-4.0.5.dist-info/top_level.txt
