Metadata-Version: 2.0
Name: closer
Version: 4.0.5
Summary: monitor and close remote SSH processes automatically
Home-page: https://haarcuba.github.io/closer
Author: Yoav Kleinberger
Author-email: haarcuba@gmail.com
License: UNKNOWN
Keywords: subprocess
Platform: UNKNOWN
Classifier: Programming Language :: Python
Classifier: Operating System :: POSIX :: Linux
Provides-Extra: testing
Requires-Dist: psutil
Requires-Dist: flask
Requires-Dist: requests
Requires-Dist: pimped-subprocess (>=2.2.0)
Provides-Extra: testing
Requires-Dist: pytest; extra == 'testing'
